decisioncanvas/__init__.py
decisioncanvas/plot_decision_boundary.py
decisioncanvas-1.0.1.dist-info/licenses/LICENSE
decisioncanvas-1.0.1.dist-info/METADATA
decisioncanvas-1.0.1.dist-info/WHEEL
decisioncanvas-1.0.1.dist-info/top_level.txt
decisioncanvas-1.0.1.dist-info/RECORD
